chocolate/__init__.py
chocolate/filter.py
chocolate-0.0.2.dist-info/METADATA
chocolate-0.0.2.dist-info/WHEEL
chocolate-0.0.2.dist-info/top_level.txt
chocolate-0.0.2.dist-info/RECORD
