Metadata-Version: 2.1
Name: chocolate
Version: 0.0.2
Summary: An improvement to Python's kwargs
Home-page: https://github.com/seungjaeryanlee/chocolate
Author: Seungjae Ryan Lee
Author-email: seungjaeryanlee@github.com
License: UNKNOWN
Platform: UNKNOWN
Classifier: Programming Language :: Python :: 3
Classifier: License :: OSI Approved :: MIT License
Classifier: Operating System :: OS Independent
Requires-Python: >=3.6
